oc_mirror/__init__.py
oc_mirror/atomicsignature.py
oc_mirror/atomicsigner.py
oc_mirror/imagestream.py
oc_mirror/ocrelease.py
oc_mirror/oprelease.py
oc_mirror/singleassignment.py
oc_mirror/specs.py
oc_mirror/utils.py
oc_mirror/scripts/__init__.py
oc_mirror/scripts/atomic.py
oc_mirror/scripts/oc_mirror.py
oc_mirror/scripts/op_mirror.py
oc_mirror/scripts/utils.py
tests/__init__.py
tests/conftest.py
tests/test_atomicsigner.py
tests/test_atomicsigner_proxy.py
tests/test_ocrelease.py
tests/test_ocrelease_proxy.py
tests/test_oprelease.py
tests/test_oprelease_proxy.py
tests/test_scripts_atomic.py
tests/test_singleassignment.py
tests/testutils.py
oc_mirror-0.1.7.dist-info/LICENSE
oc_mirror-0.1.7.dist-info/METADATA
oc_mirror-0.1.7.dist-info/WHEEL
oc_mirror-0.1.7.dist-info/entry_points.txt
oc_mirror-0.1.7.dist-info/top_level.txt
oc_mirror-0.1.7.dist-info/RECORD
