Metadata-Version: 2.1
Name: oc-mirror
Version: 0.1.7
Summary: A utility that can be used to mirror OpenShift releases between docker registries.
Home-page: https://pypi.org/project/oc-mirror/
Author: Richard Davis
Author-email: crashvb@gmail.com
License: GNU General Public License v3.0
Project-URL: Bug Reports, https://github.com/crashvb/oc-mirror/issues
Project-URL: Source, https://github.com/crashvb/oc-mirror
Keywords: integrity mirror oc oc-mirror openshift sign signatures verify
Platform: UNKNOWN
Classifier: Development Status :: 4 - Beta
Classifier: Intended Audience :: Developers
Classifier: License :: OSI Approved :: GNU General Public License v3 or later (GPLv3+)
Classifier: Programming Language :: Python :: 3
Classifier: Programming Language :: Python :: 3.8
Classifier: Programming Language :: Python :: 3.9
Classifier: Programming Language :: Python :: 3.10
Classifier: Operating System :: OS Independent
Requires-Dist: aiofiles
Requires-Dist: click
Requires-Dist: docker-registry-client-async (>=0.2.3)
Requires-Dist: docker-sign-verify (>=2.0.4)
Requires-Dist: pretty-bad-protocol (>=3.1.1)
Requires-Dist: pyyaml
Provides-Extra: dev
Requires-Dist: black ; extra == 'dev'
Requires-Dist: coveralls ; extra == 'dev'
Requires-Dist: pylint ; extra == 'dev'
Requires-Dist: pyopenssl ; extra == 'dev'
Requires-Dist: pytest ; extra == 'dev'
Requires-Dist: pytest-asyncio ; extra == 'dev'
Requires-Dist: pytest-docker-apache-fixtures ; extra == 'dev'
Requires-Dist: pytest-docker-registry-fixtures ; extra == 'dev'
Requires-Dist: pytest-docker-squid-fixtures (>=0.1.2) ; extra == 'dev'
Requires-Dist: pytest-gnupg-fixtures ; extra == 'dev'
Requires-Dist: twine ; extra == 'dev'
Requires-Dist: wheel ; extra == 'dev'
